LICENSE.txt
MANIFEST.in
requirements.txt
setup.cfg
setup.py
checkio_docker/__init__.py
checkio_docker/client.py
checkio_docker/container.py
checkio_docker/parser.py
checkio_docker/utils.py
checkio_docker.egg-info/PKG-INFO
checkio_docker.egg-info/SOURCES.txt
checkio_docker.egg-info/dependency_links.txt
checkio_docker.egg-info/requires.txt
checkio_docker.egg-info/top_level.txt