Metadata-Version: 1.1
Name: checkio-docker
Version: 0.0.14
Summary: Build docker images from CheckiO mission module
Home-page: https://github.com/CheckiO/checkio-docker
Author: CheckiO
Author-email: igor@checkio.org
License: UNKNOWN
Download-URL: https://github.com/CheckiO/checkio-docker/tarball/0.0.14
Platform: UNKNOWN
